LICENSE
default_mutable/DefaultMutable.py
default_mutable/__init__.py
default_mutable-0.1.0.dist-info/LICENSE
default_mutable-0.1.0.dist-info/WHEEL
default_mutable-0.1.0.dist-info/METADATA
default_mutable-0.1.0.dist-info/RECORD
