Metadata-Version: 2.1
Name: default-mutable
Version: 0.1.0
Summary: Prevent mutable default arguments behavior
Home-page: https://github.com/roodrepo/default_mutable
License: MIT
Keywords: default arguments,default list,default dict,decorator
Author: Rood Repo
Author-email: roodrepo@gmail.com
Requires-Python: >=3,<4
Classifier: Intended Audience :: Developers
Classifier: License :: OSI Approved :: MIT License
Classifier: Operating System :: OS Independent
Classifier: Programming Language :: Python :: 3
Classifier: Programming Language :: Python :: 3.10
Classifier: Programming Language :: Python :: 3.4
Classifier: Programming Language :: Python :: 3.5
Classifier: Programming Language :: Python :: 3.6
Classifier: Programming Language :: Python :: 3.7
Classifier: Programming Language :: Python :: 3.8
Classifier: Programming Language :: Python :: 3.9
Classifier: Topic :: Software Development :: Libraries :: Python Modules
Project-URL: Repository, https://github.com/roodrepo/default_mutable
